sandpyper/__init__.py
sandpyper/common.py
sandpyper/sandpyper.py
sandpyper-1.3.3.dist-info/LICENSE
sandpyper-1.3.3.dist-info/METADATA
sandpyper-1.3.3.dist-info/WHEEL
sandpyper-1.3.3.dist-info/dependency_links.txt
sandpyper-1.3.3.dist-info/top_level.txt
sandpyper-1.3.3.dist-info/RECORD
