Metadata-Version: 2.1
Name: sandpyper
Version: 1.3.3
Summary: Tools for automatic UAV-SfM beach volumetric and behavioural analysis.
Home-page: https://github.com/npucino/sandpyper
Author: Nicolas Pucino
Author-email: npucino@deakin.edu.au
License: MIT license
Keywords: sandpyper beach analysis SfM raster volume profiles UAV drone monitoring
Platform: UNKNOWN
Classifier: Development Status :: 2 - Pre-Alpha
Classifier: Intended Audience :: Science/Research
Classifier: License :: OSI Approved :: MIT License
Classifier: Natural Language :: English
Classifier: Programming Language :: Python :: 3.8
Requires-Python: >=3.8
License-File: LICENSE
